dfagent/__init__.py
dfagent/dfagent.py
dfagent-0.1.dist-info/LICENSE
dfagent-0.1.dist-info/METADATA
dfagent-0.1.dist-info/WHEEL
dfagent-0.1.dist-info/top_level.txt
dfagent-0.1.dist-info/RECORD
