Metadata-Version: 2.1
Name: dfagent
Version: 0.1
Summary: Dialogflow agent is a library for online or offline handling of Dialogflow agents.
Home-page: https://github.com/aitechnologies-it/dialogflow-agent
Author: Luigi Di Sotto, Diego Giorgini
Author-email: luigi.disotto@aitechnologies.it, diego.giorgini@aitechnologies.it
License: UNKNOWN
Platform: UNKNOWN
Classifier: Intended Audience :: Developers
Classifier: Intended Audience :: Education
Classifier: Intended Audience :: Science/Research
Classifier: License :: OSI Approved :: MIT License
Classifier: Operating System :: OS Independent
Classifier: Programming Language :: Python :: 3
Classifier: Programming Language :: Python :: 3.6
Classifier: Programming Language :: Python :: 3.7
Classifier: Topic :: Scientific/Engineering :: Artificial Intelligence
Requires-Python: >=3.8
Requires-Dist: google (==3.0.0)
Requires-Dist: dialogflow (==1.1.0)
Requires-Dist: tqdm (==4.56.0)
Requires-Dist: coloredlogs (==15.0)
Requires-Dist: pydlib
Requires-Dist: funcy
